speedyPort/__init__.py
speedyPort/app.py
speedyPort-1.0.0.dist-info/METADATA
speedyPort-1.0.0.dist-info/WHEEL
speedyPort-1.0.0.dist-info/entry_points.txt
speedyPort-1.0.0.dist-info/top_level.txt
speedyPort-1.0.0.dist-info/RECORD
